rem/__init__.py
rem/config.py
rem/mcp_server.py
rem/py.typed
rem/registry.py
rem/settings.py
rem/agentic/README.md
rem/agentic/__init__.py
rem/agentic/context.py
rem/agentic/context_builder.py
rem/agentic/llm_provider_models.py
rem/agentic/query.py
rem/agentic/query_helper.py
rem/agentic/schema.py
rem/agentic/serialization.py
rem/agentic/agents/README.md
rem/agentic/agents/__init__.py
rem/agentic/agents/agent_manager.py
rem/agentic/agents/moment_builder.py
rem/agentic/agents/sse_simulator.py
rem/agentic/mcp/__init__.py
rem/agentic/mcp/tool_wrapper.py
rem/agentic/otel/__init__.py
rem/agentic/otel/setup.py
rem/agentic/providers/phoenix.py
rem/agentic/providers/pydantic_ai.py
rem/agentic/tools/__init__.py
rem/agentic/tools/rem_tools.py
rem/api/README.md
rem/api/deps.py
rem/api/main.py
rem/api/mcp_router/prompts.py
rem/api/mcp_router/resources.py
rem/api/mcp_router/server.py
rem/api/mcp_router/tools.py
rem/api/middleware/tracking.py
rem/api/routers/admin.py
rem/api/routers/auth.py
rem/api/routers/common.py
rem/api/routers/dev.py
rem/api/routers/feedback.py
rem/api/routers/messages.py
rem/api/routers/models.py
rem/api/routers/moments.py
rem/api/routers/query.py
rem/api/routers/shared_sessions.py
rem/api/routers/chat/__init__.py
rem/api/routers/chat/child_streaming.py
rem/api/routers/chat/completions.py
rem/api/routers/chat/json_utils.py
rem/api/routers/chat/models.py
rem/api/routers/chat/otel_utils.py
rem/api/routers/chat/sse_events.py
rem/api/routers/chat/streaming.py
rem/api/routers/chat/streaming_utils.py
rem/auth/README.md
rem/auth/__init__.py
rem/auth/jwt.py
rem/auth/middleware.py
rem/auth/providers/__init__.py
rem/auth/providers/base.py
rem/auth/providers/email.py
rem/auth/providers/google.py
rem/auth/providers/microsoft.py
rem/cli/README.md
rem/cli/__init__.py
rem/cli/dreaming.py
rem/cli/main.py
rem/cli/commands/README.md
rem/cli/commands/__init__.py
rem/cli/commands/ask.py
rem/cli/commands/cluster.py
rem/cli/commands/configure.py
rem/cli/commands/db.py
remdb-0.3.270.dist-info/METADATA
remdb-0.3.270.dist-info/WHEEL
remdb-0.3.270.dist-info/entry_points.txt
remdb-0.3.270.dist-info/RECORD
