Metadata-Version: 2.4
Name: remdb
Version: 0.3.270
Summary: Resources Entities Moments - Bio-inspired memory system for agentic AI workloads
Project-URL: Homepage, https://github.com/Percolation-Labs/reminiscent
Project-URL: Documentation, https://github.com/Percolation-Labs/reminiscent/blob/main/README.md
Project-URL: Repository, https://github.com/Percolation-Labs/reminiscent
Project-URL: Issues, https://github.com/Percolation-Labs/reminiscent/issues
Author-email: mr-saoirse <amartey@gmail.com>
License: MIT
Keywords: agents,ai,mcp,memory,postgresql,vector-search
Classifier: Development Status :: 3 - Alpha
Classifier: Intended Audience :: Developers
Classifier: License :: OSI Approved :: MIT License
Classifier: Programming Language :: Python :: 3.11
Classifier: Programming Language :: Python :: 3.12
Classifier: Programming Language :: Python :: 3.13
Classifier: Topic :: Scientific/Engineering :: Artificial Intelligence
Requires-Python: <3.14,>=3.11
Requires-Dist: aioboto3>=13.0.0
Requires-Dist: arize-phoenix>=5.0.0
Requires-Dist: asyncpg>=0.30.0
Requires-Dist: boto3>=1.35.0
Requires-Dist: click>=8.1.0
Requires-Dist: fastapi>=0.115.0
Requires-Dist: fastmcp>=0.5.0
Requires-Dist: gitpython>=3.1.45
Requires-Dist: hypercorn>=0.17.0
Requires-Dist: itsdangerous>=2.0.0
Requires-Dist: json-schema-to-pydantic>=0.2.0
Requires-Dist: kreuzberg>=4.0.5
Requires-Dist: loguru>=0.7.0
Requires-Dist: openinference-instrumentation-pydantic-ai>=0.1.0
Requires-Dist: opentelemetry-api>=1.28.0
Requires-Dist: opentelemetry-exporter-otlp-proto-grpc>=1.28.0
Requires-Dist: opentelemetry-exporter-otlp-proto-http>=1.28.0
Requires-Dist: opentelemetry-exporter-otlp>=1.28.0
Requires-Dist: opentelemetry-instrumentation-fastapi>=0.49b0
Requires-Dist: opentelemetry-instrumentation>=0.49b0
Requires-Dist: opentelemetry-sdk>=1.28.0
Requires-Dist: psycopg[binary]>=3.2.0
Requires-Dist: pydantic-ai>=1.0.0
Requires-Dist: pydantic-settings>=2.6.0
Requires-Dist: pydantic>=2.10.0
Requires-Dist: pydub>=0.25.0
Requires-Dist: pymupdf>=1.24.0
Requires-Dist: python-dotenv>=1.0.0
Requires-Dist: pyyaml>=6.0.0
Requires-Dist: requests>=2.32.0
Requires-Dist: semchunk>=2.2.0
Requires-Dist: tenacity>=9.0.0
Requires-Dist: tiktoken>=0.5.0
Requires-Dist: uvicorn[standard]>=0.32.0
Provides-Extra: all
Requires-Dist: ipdb>=0.13.0; extra == 'all'
Requires-Dist: ipython>=8.29.0; extra == 'all'
Requires-Dist: json-schema-to-pydantic>=0.2.0; extra == 'all'
Requires-Dist: mypy>=1.13.0; extra == 'all'
Requires-Dist: pandas-stubs>=2.0.0; extra == 'all'
Requires-Dist: pillow>=10.0.0; extra == 'all'
Requires-Dist: polars>=1.0.0; extra == 'all'
Requires-Dist: pydub>=0.25.0; extra == 'all'
Requires-Dist: pytest-asyncio>=0.24.0; extra == 'all'
Requires-Dist: pytest-cov>=6.0.0; extra == 'all'
Requires-Dist: pytest-mock>=3.14.0; extra == 'all'
Requires-Dist: pytest>=8.0.0; extra == 'all'
Requires-Dist: ruff>=0.8.0; extra == 'all'
Requires-Dist: types-pyyaml>=6.0.0; extra == 'all'
Provides-Extra: audio
Requires-Dist: pydub>=0.25.0; extra == 'audio'
Provides-Extra: dev
Requires-Dist: ipdb>=0.13.0; extra == 'dev'
Requires-Dist: ipython>=8.29.0; extra == 'dev'
Requires-Dist: mypy>=1.13.0; extra == 'dev'
Requires-Dist: pandas-stubs>=2.0.0; extra == 'dev'
Requires-Dist: pytest-asyncio>=0.24.0; extra == 'dev'
Requires-Dist: pytest-cov>=6.0.0; extra == 'dev'
Requires-Dist: pytest-mock>=3.14.0; extra == 'dev'
Requires-Dist: pytest>=8.0.0; extra == 'dev'
Requires-Dist: ruff>=0.8.0; extra == 'dev'
Requires-Dist: types-pyyaml>=6.0.0; extra == 'dev'
Provides-Extra: fs
Requires-Dist: pillow>=10.0.0; extra == 'fs'
Requires-Dist: polars>=1.0.0; extra == 'fs'
Requires-Dist: pydub>=0.25.0; extra == 'fs'
Provides-Extra: schema
Requires-Dist: json-schema-to-pydantic>=0.2.0; extra == 'schema'
